hello.py
hello_carla-0.2.data/scripts/sayhello
hello_carla-0.2.dist-info/METADATA
hello_carla-0.2.dist-info/WHEEL
hello_carla-0.2.dist-info/top_level.txt
hello_carla-0.2.dist-info/RECORD
