Metadata-Version: 2.1
Name: hello-carla
Version: 0.2
Summary: Hello world test of pip org
Home-page: 
Author: Carla Dias
Author-email: carlamione@gmail.com
License: UNKNOWN
Platform: UNKNOWN
Classifier: Programming Language :: Python :: 3
Classifier: License :: OSI Approved :: MIT License
Classifier: Operating System :: OS Independent
